Metadata-Version: 2.1
Name: featurebox
Version: 0.1.6
Summary: This is an box contains tools for machine learning.Some of code are non-originality, just copy for use. All the referenced code are marked,details can be shown in their sources
Home-page: https://github.com/boliqq07/featurebox
Author: wangchangxin
Author-email: 986798607@qq.com
Maintainer: wangchangxin
Keywords: features,combination,selection
Platform: Windows
Platform: Unix
Classifier: Development Status :: 4 - Beta
Classifier: Intended Audience :: Science/Research
Classifier: License :: OSI Approved :: GNU General Public License v3 (GPLv3)
Classifier: Natural Language :: English
Classifier: Operating System :: Microsoft :: Windows
Classifier: Operating System :: Unix
Classifier: Programming Language :: Python :: 3.6
Classifier: Programming Language :: Python :: 3.7
Classifier: Programming Language :: Python :: 3.8
Classifier: Programming Language :: Python :: 3.9
Classifier: Programming Language :: Python :: 3.10
Classifier: Programming Language :: Python :: 3.11
Classifier: Programming Language :: Python :: 3.12
Requires-Python: >=3.6
License-File: LICENSE
